setup.py
streetvoice_celery_email.egg-info/PKG-INFO
streetvoice_celery_email.egg-info/SOURCES.txt
streetvoice_celery_email.egg-info/dependency_links.txt
streetvoice_celery_email.egg-info/not-zip-safe
streetvoice_celery_email.egg-info/top_level.txt
svcelery_email/__init__.py
svcelery_email/admin.py
svcelery_email/backends.py
svcelery_email/models.py
svcelery_email/tasks.py
svcelery_email/tests.py
svcelery_email/views.py