Metadata-Version: 1.1
Name: streetvoice-celery-email
Version: 0.3.6
Summary: streetvoice-celery-email
Home-page: http://github.com/tzangms/streetvoice-celery-email
Author: tzangms
Author-email: tzangms@gmail.com
License: BSD
Keywords: django,celery,mail
Platform: UNKNOWN
Classifier: Programming Language :: Python
Classifier: Topic :: Software Development :: Libraries :: Python Modules
Classifier: Framework :: Django
Classifier: Environment :: Web Environment
